research_utils/__init__.py
research_utils/argparse/__init__.py
research_utils/argparse/actions/__init__.py
research_utils/argparse/actions/enum.py
research_utils/argparse/actions/yaml.py
research_utils/decorators/__init__.py
research_utils/decorators/arguments.py
research_utils/decorators/logging.py
research_utils/sqlite/__init__.py
research_utils/sqlite/functional.py
research_utils/sqlite/helper.py
research_utils/sqlite/row_factory.py
research_utils/sqlite/typing/__init__.py
research_utils/sqlite/typing/operator.py
research_utils/sqlite/typing/sql.py
research_utils/sqlite/utils.py
research_utils/sqlite/yaml.py
research_utils/torch/__init__.py
research_utils/torch/db_folder.py
research_utils/torch/modeling.py
research_utils/utils.py
research_utils-2021.11.24.5.dist-info/WHEEL
research_utils-2021.11.24.5.dist-info/METADATA
research_utils-2021.11.24.5.dist-info/RECORD
