Metadata-Version: 2.1
Name: research-utils
Version: 2021.11.24.5
Summary: some utils for my research
Home-page: https://r08521610.github.io/research-utils/
Author: Rainforest Cheng
Author-email: r08521610@ntu.edu.tw
Requires-Python: >=3.7,<4.0
Classifier: Programming Language :: Python :: 3
Classifier: Programming Language :: Python :: 3.10
Classifier: Programming Language :: Python :: 3.7
Classifier: Programming Language :: Python :: 3.8
Classifier: Programming Language :: Python :: 3.9
Requires-Dist: PyYAML (>=6.0,<7.0)
Requires-Dist: sqlite-utils (>=3.6,<4.0)
Project-URL: Repository, https://github.com/r08521610/research-utils
